{
  "updates": {
    "tt001": {
      "special_powers": [{
        "powers": ["incapacitate", "smoke_cloud"]
      }]
    },
    "tt003": {
      "special_powers": [{
        "powers": ["shape_change"]
      }]
    },
    "tt006": {
      "special_powers": [{
        "powers": ["outwit"]
      }]
    },
    "tt009": {
      "special_powers": [{
      }, {
        "powers": ["willpower"]
      }]
    },
    "tt010": {
      "special_powers": [{
        "powers": ["exploit_weakness", "willpower"]
      }]
    },
    "tt011": {
      "special_powers": [{
        "powers": ["willpower"]
      }]
    },
    "tt018": {
      "special_powers": [{
        "powers": ["outwit"]
      }]
    },
    "tt020": {
      "special_powers": [{
      }, {
        "powers": ["perplex", "close_combat_expert", "quake"]
      }]
    },
    "tt021": {
      "special_powers": [{
      }, {
        "powers": ["leap_climb"]
      }]
    },
    "tt027": {
      "special_powers": [{
        "description": "Centerhall can use Leadership. He succeeds on a roll of 4-6 if another character on your force possesses the N.O.W.H.E.R.E. keyword.",
        "powers": ["leadership"]
      }]
    },
    "tt030": {
      "special_powers": [{
        "powers": ["super_senses"]
      }]
    },
    "tt032": {
      "special_powers": [{
      }, {
        "powers": ["super_senses"]
      }]
    },
    "tt034": {
      "special_powers": [{
        "powers": ["toughness", "invulnerability", "impervious"]
      }]
    },
    "tt035": {
      "special_powers": [{
        "powers": ["toughness"]
      }]
    },
    "tt038": {
      "special_powers": [{
      }, {
        "description": "Changeling can use Charge and Close Combat Expert. When he uses Charge he can use Improved Movement: Characters."
      }]
    },
    "tt043": {
      "special_powers": [{
        "powers": ["leap_climb", "quake"]
      }]
    },
    "tt044": {
      "special_powers": [{
      }, {
        "powers": ["blades_claws_fangs", "energy_explosion", "pulse_wave", "quake", "super_strength", "incapacitate", "penetrating_psychic_blast", "smoke_cloud", "precision_strike", "poison", "steal_energy", "telekinesis", "ranged_combat_expert", "battle_fury", "support", "exploit_weakness", "enhancement", "probability_control", "shape_change", "close_combat_expert", "empower", "perplex", "outwit", "leadership"]
      }]
    },
    "tt050": {
      "special_powers": [{
        "description": "Flash can use Charge, Flurry, and Phasing/Teleport. When Flash uses Charge, he can use Improved Movement: Hindering.",
        "powers": ["charge", "flurry", "phasing_teleport"]
      }, {
        "powers": ["combat_reflexes", "shape_change"]
      }]
    },
    "tt054": {
      "special_powers": [{
        "powers": ["stealth"]
      }]
    },
    "tt058": {
      "special_powers": [{
        "powers": ["pulse_wave"]
      }]
    },
    "tt060": {
      "special_powers": [{
      }, {
        "description": "Persuader can use Improved Movement: Characters. When making a close combat attack, Persuader treats characters 2 squares and line of fire as adjacent."
      }]
    },
    "tt064": {
      "special_powers": [{
      }, {
        "powers": ["super_senses"]
      }]
    },
    "tt068": {
      "special_powers": [{
        "powers": ["willpower"]
      }, {
      }, {
        "powers": ["incapacitate", "perplex"]
      }]
    },
    "tt071": {
      "special_powers": [{
      }, {
        "powers": ["close_combat_expert", "exploit_weakness", "perplex", "shape_change"]
      }]
    },
    "tt201": {
      "special_powers": [{
        "powers": ["running_shot", "willpower"]
      }]
    },
    "tt203": {
      "special_powers": [{
        "description": "Wonder Girl can use Charge. When she does, she can use Improved Movement: Characters, Destroy Blocking."
      }, {
        "powers": ["impervious", "invulnerability", "toughness"]
      }]
    },
    "tt206": {
      "special_powers": [{
        "powers": ["poison", "willpower"]
      }]
    },
    "tt208": {
      "special_powers": [{
      }, {
      }, {
        "powers": ["combat_reflexes", "super_senses"]
      }]
    },
    "ttG001": {
      "special_powers": [{
      }, {
      }, {
        "powers": ["regeneration", "super_senses"]
      }]
    },
    "ttT001": {
      "special_powers": [{
      }, {
      }, {
        "powers": ["outwit", "perplex", "probability_control"]
      }, {
      }, {
      }, {
      }, {
        "powers": ["regeneration"]
      }]
    },
    "ttT003": {
      "special_powers": [{
      }, {
      }, {
        "description": "Titans: Villains for Hire can use Toughness and Regeneration.",
        "powers": ["toughness", "regeneration"]
      }, {
        "description": "Titans: Villains for Hire can use Poison. When they do, damage dealt to The Mark is penetrating damage.",
        "powers": ["poison"]
      }, {
        "description": "Titans: Villains for Hire can use Phasing/Teleport. Lines of fire drawn by Titans: Villains for Hire to The Mark ignore blocking terrain.",
        "powers": ["phasing_teleport"]
      }, {
        "description": "Titans: Villains for Hire can use Outwit. When Titans Villains for Hire attack the Mark modify their attack and damage values by +1.",
        "powers": ["outwit"]
      }, {
        "description": "Titans: Villains for Hire can use Charge. After Titans: Villains for Hire resolve a move action, if they are adjacent to The Mark, you may give them a close combat action as a free action.",
        "powers": ["charge"]
      }, {
        "description": "Titans: Villains for Hire can use Shape Change. When Titans: Villains for Hire are attacked by The Mark, they succeed for Shape Change on a result of 4 - 6.",
        "powers": ["shape_change"]
      }]
    },
    "ttT004": {
      "special_powers": [{
      }, {
      }, {
      }, {
      }, {
      }, {
        "powers": ["energy_explosion"]
      }, {
        "powers": ["perplex"]
      }]
    },
    "ttT006": {
      "special_powers": [{
      }, {
        "powers": ["combat_reflexes", "super_senses"]
      }, {
      }, {
      }, {
      }, {
        "powers": ["outwit"]
      }]
    }
  },
  "additions": [{
    "unit_id": "ttM001",
    "set_id": "tt",
    "collector_number": "M001",
    "name": "N.O.W.H.E.R.E.: The Crucible",
    "type": "map",
    "special_powers": [{
      "description": "Orange squares are Lava Squares. At the end of each player's turn, deal 1 unavoidable damage to each character occupying a Lava Square."
    }],
    "map_url": "https://hcmaps.net/maps/tt/nowhere_the_crucible.json"
  }, {
    "unit_id": "ttM002",
    "set_id": "tt",
    "collector_number": "M002",
    "name": "Teen Titans Tower: Great Hall",
    "type": "map",
    "map_url": "https://hcmaps.net/maps/tt/teen_titans_tower_great_hall.json"
  }, {
    "unit_id": "ttM003",
    "set_id": "tt",
    "collector_number": "M003",
    "name": "N.O.W.H.E.R.E.:Omen's Domain",
    "type": "map",
    "map_url": "https://hcmaps.net/maps/tt/nowhere_omens_domain.json"
  }, {
    "unit_id": "ttM004",
    "set_id": "tt",
    "collector_number": "M004",
    "name": "Teen Titans Tower: Memorial Hall",
    "type": "map",
    "map_url": "https://hcmaps.net/maps/tt/teen_titans_tower_memorial_hall.json"
  }, {
    "unit_id": "ttM005",
    "set_id": "tt",
    "collector_number": "M005",
    "name": "N.O.W.H.E.R.E.: Project Superboy Laboratory",
    "type": "map",
    "map_url": "https://hcmaps.net/maps/tt/nowhere_project_superboy_laboratory.json"
  }, {
    "unit_id": "ttM006",
    "set_id": "tt",
    "collector_number": "M006",
    "name": "Teen Titans Tower: Laboratory Level",
    "type": "map",
    "map_url": "https://hcmaps.net/maps/tt/teen_titans_tower_laboratory_level.json"
  }, {
    "unit_id": "ttM007",
    "set_id": "tt",
    "collector_number": "M007",
    "name": "N.O.W.H.E.R.E.: Harvest's Domain",
    "type": "map",
    "map_url": "https://hcmaps.net/maps/tt/nowhere_harvests_domain.json"
  }, {
    "unit_id": "ttM008",
    "set_id": "tt",
    "collector_number": "M008",
    "name": "Teen Titans Tower: Sub-Basement Level",
    "type": "map",
    "map_url": "https://hcmaps.net/maps/tt/teen_titans_tower_sub_basement_level.json"
  }, {
    "unit_id": "ttM009",
    "set_id": "tt",
    "collector_number": "M009",
    "name": "N.O.W.H.E.R.E.: Holding Cells",
    "type": "map",
    "map_url": "https://hcmaps.net/maps/tt/nowhere_holding_cells.json"
  }, {
    "unit_id": "ttM010",
    "set_id": "tt",
    "collector_number": "M010",
    "name": "Teen Titans Tower: Residential Level",
    "type": "map",
    "map_url": "https://hcmaps.net/maps/tt/teen_titans_tower_residential_level.json"
  }, {
    "unit_id": "ttM011",
    "set_id": "tt",
    "collector_number": "M011",
    "name": "N.O.W.H.E.R.E.: Control Room",
    "type": "map",
    "map_url": "https://hcmaps.net/maps/tt/nowhere_control_room.json"
  }, {
    "unit_id": "ttM012",
    "set_id": "tt",
    "collector_number": "M012",
    "name": "Teen Titans Tower: Recreation Level",
    "type": "map",
    "map_url": "https://hcmaps.net/maps/tt/teen_titans_tower_recreation_level.json"
  }]
}
