{
  "updates": {
    "em023": {
      "special_powers": [{
      }, {
        "description": "At the beginning of your turn, choose one to use this turn: Close Combat Expert, Ranged Combat Expert, or Colossal Stamina. // At the beginning of your turn, if Uni-Mind has 2 action tokens, choose one that you didn't choose on your last turn to use this turn: Phasing/Teleport as FREE or Regeneration as FREE.",
        "powers": ["close_combat_expert", "ranged_combat_expert", "phasing_teleport", "regeneration"]
      }]
    }
  }
}
