<resultset>
  <row>
    <unit_id>ffgl001</unit_id>
    <set_id>ffgl</set_id>
    <collector_number>001</collector_number>
    <name>Green Lantern</name>
    <type>character</type>
    <rarity>common</rarity>
    <dimensions>1x1</dimensions>
    <point_values>[125]</point_values>
    <properties>[]</properties>
    <team_abilities>[]</team_abilities>
    <keywords>["Green Lantern Corps", "Police"]</keywords>
    <special_powers>[]</special_powers>
    <improved_movement>[]</improved_movement>
    <improved_targeting>[]</improved_targeting>
    <object_keyphrases>[]</object_keyphrases>
    <unit_range>8</unit_range>
    <targets>1</targets>
    <speed_type>wing</speed_type>
    <attack_type>fist</attack_type>
    <defense_type>indomitable</defense_type>
    <damage_type>starburst</damage_type>
    <dial_size>12</dial_size>
    <dial>[
  {
    "click_number": 1, 
    "starting_line": true, 
    "speed_power": "phasing_teleport", 
    "speed_value": 9, 
    "attack_power": "telekinesis", 
    "attack_value": 10, 
    "defense_power": "toughness", 
    "defense_value": 18, 
    "damage_power": "ranged_combat_expert", 
    "damage_value": 3
  }, 
  {
    "click_number": 2, 
    "speed_power": "running_shot", 
    "speed_value": 9, 
    "attack_power": "telekinesis", 
    "attack_value": 10, 
    "defense_power": "toughness", 
    "defense_value": 18, 
    "damage_power": "ranged_combat_expert", 
    "damage_value": 3
  }, 
  {
    "click_number": 3, 
    "speed_power": "running_shot", 
    "speed_value": 9, 
    "attack_power": "incapacitate", 
    "attack_value": 9, 
    "defense_power": "toughness", 
    "defense_value": 17, 
    "damage_power": "ranged_combat_expert", 
    "damage_value": 3
  }, 
  {
    "click_number": 4, 
    "speed_value": 9, 
    "attack_power": "incapacitate", 
    "attack_value": 9, 
    "defense_power": "toughness", 
    "defense_value": 17, 
    "damage_power": "ranged_combat_expert", 
    "damage_value": 2
  }, 
  {
    "click_number": 5, 
    "speed_power": "phasing_teleport", 
    "speed_value": 9, 
    "attack_power": "penetrating_psychic_blast", 
    "attack_value": 9, 
    "defense_power": "energy_shield_deflection", 
    "defense_value": 17, 
    "damage_power": "perplex", 
    "damage_value": 2
  }, 
  {
    "click_number": 6, 
    "speed_power": "phasing_teleport", 
    "speed_value": 9, 
    "attack_power": "penetrating_psychic_blast", 
    "attack_value": 9, 
    "defense_power": "energy_shield_deflection", 
    "defense_value": 16, 
    "damage_power": "perplex", 
    "damage_value": 2
  }, 
  {
    "click_number": 7, 
    "speed_power": "phasing_teleport", 
    "speed_value": 9, 
    "attack_power": "energy_explosion", 
    "attack_value": 9, 
    "defense_power": "energy_shield_deflection", 
    "defense_value": 16, 
    "damage_power": "perplex", 
    "damage_value": 2
  }, 
  {
    "click_number": 8, 
    "speed_power": "phasing_teleport", 
    "speed_value": 9, 
    "attack_power": "energy_explosion", 
    "attack_value": 8, 
    "defense_power": "energy_shield_deflection", 
    "defense_value": 16, 
    "damage_power": "perplex", 
    "damage_value": 2
  }
]</dial>
  </row>
  <row>
    <unit_id>ffgl002</unit_id>
    <set_id>ffgl</set_id>
    <collector_number>002</collector_number>
    <name>Kilowog</name>
    <type>character</type>
    <rarity>common</rarity>
    <dimensions>1x1</dimensions>
    <point_values>[100]</point_values>
    <properties>[]</properties>
    <team_abilities>[]</team_abilities>
    <keywords>["Brute", "Green Lantern Corps", "Police"]</keywords>
    <special_powers>[]</special_powers>
    <improved_movement>[]</improved_movement>
    <improved_targeting>[]</improved_targeting>
    <object_keyphrases>[]</object_keyphrases>
    <unit_range>7</unit_range>
    <targets>1</targets>
    <speed_type>wing</speed_type>
    <attack_type>fist</attack_type>
    <defense_type>shield</defense_type>
    <damage_type>starburst</damage_type>
    <dial_size>12</dial_size>
    <dial>[
  {
    "click_number": 1, 
    "starting_line": true, 
    "speed_power": "charge", 
    "speed_value": 10, 
    "attack_power": "telekinesis", 
    "attack_value": 11, 
    "defense_power": "invulnerability", 
    "defense_value": 17, 
    "damage_value": 4
  }, 
  {
    "click_number": 2, 
    "speed_power": "charge", 
    "speed_value": 10, 
    "attack_power": "super_strength", 
    "attack_value": 10, 
    "defense_power": "invulnerability", 
    "defense_value": 17, 
    "damage_value": 3
  }, 
  {
    "click_number": 3, 
    "speed_power": "charge", 
    "speed_value": 10, 
    "attack_power": "super_strength", 
    "attack_value": 10, 
    "defense_power": "toughness", 
    "defense_value": 16, 
    "damage_value": 3
  }, 
  {
    "click_number": 4, 
    "speed_power": "charge", 
    "speed_value": 10, 
    "attack_power": "super_strength", 
    "attack_value": 10, 
    "defense_power": "toughness", 
    "defense_value": 16, 
    "damage_value": 3
  }, 
  {
    "click_number": 5, 
    "speed_power": "flurry", 
    "speed_value": 9, 
    "attack_value": 9, 
    "defense_power": "willpower", 
    "defense_value": 17, 
    "damage_power": "enhancement", 
    "damage_value": 3
  }, 
  {
    "click_number": 6, 
    "speed_power": "flurry", 
    "speed_value": 9, 
    "attack_value": 9, 
    "defense_power": "willpower", 
    "defense_value": 16, 
    "damage_power": "enhancement", 
    "damage_value": 2
  }, 
  {
    "click_number": 7, 
    "speed_power": "flurry", 
    "speed_value": 9, 
    "attack_value": 8, 
    "defense_power": "willpower", 
    "defense_value": 16, 
    "damage_power": "enhancement", 
    "damage_value": 2
  }
]</dial>
  </row>
  <row>
    <unit_id>ffgl003</unit_id>
    <set_id>ffgl</set_id>
    <collector_number>003</collector_number>
    <name>Tomar Re</name>
    <type>character</type>
    <rarity>common</rarity>
    <dimensions>1x1</dimensions>
    <point_values>[75]</point_values>
    <properties>[]</properties>
    <team_abilities>[]</team_abilities>
    <keywords>["Green Lantern Corps", "Scientist"]</keywords>
    <special_powers>[]</special_powers>
    <improved_movement>[]</improved_movement>
    <improved_targeting>[]</improved_targeting>
    <object_keyphrases>[]</object_keyphrases>
    <unit_range>9</unit_range>
    <targets>2</targets>
    <speed_type>wing</speed_type>
    <attack_type>fist</attack_type>
    <defense_type>shield</defense_type>
    <damage_type>starburst</damage_type>
    <dial_size>12</dial_size>
    <dial>[
  {
    "click_number": 1, 
    "starting_line": true, 
    "speed_power": "running_shot", 
    "speed_value": 10, 
    "attack_power": "energy_explosion", 
    "attack_value": 10, 
    "defense_power": "energy_shield_deflection", 
    "defense_value": 17, 
    "damage_value": 3
  }, 
  {
    "click_number": 2, 
    "speed_power": "force_blast", 
    "speed_value": 10, 
    "attack_power": "energy_explosion", 
    "attack_value": 10, 
    "defense_power": "energy_shield_deflection", 
    "defense_value": 16, 
    "damage_value": 3
  }, 
  {
    "click_number": 3, 
    "speed_power": "force_blast", 
    "speed_value": 9, 
    "attack_power": "energy_explosion", 
    "attack_value": 9, 
    "defense_power": "toughness", 
    "defense_value": 16, 
    "damage_value": 2
  }, 
  {
    "click_number": 4, 
    "speed_power": "force_blast", 
    "speed_value": 9, 
    "attack_power": "incapacitate", 
    "attack_value": 9, 
    "defense_power": "toughness", 
    "defense_value": 16, 
    "damage_value": 2
  }, 
  {
    "click_number": 5, 
    "speed_power": "force_blast", 
    "speed_value": 8, 
    "attack_power": "incapacitate", 
    "attack_value": 9, 
    "defense_power": "toughness", 
    "defense_value": 15, 
    "damage_value": 2
  }, 
  {
    "click_number": 6, 
    "speed_value": 8, 
    "attack_power": "incapacitate", 
    "attack_value": 9, 
    "defense_power": "toughness", 
    "defense_value": 15, 
    "damage_value": 2
  }
]</dial>
  </row>
  <row>
    <unit_id>ffgl004</unit_id>
    <set_id>ffgl</set_id>
    <collector_number>004</collector_number>
    <name>Sinestro</name>
    <type>character</type>
    <rarity>common</rarity>
    <dimensions>1x1</dimensions>
    <point_values>[100]</point_values>
    <properties>[]</properties>
    <team_abilities>[]</team_abilities>
    <keywords>["Green Lantern Corps"]</keywords>
    <special_powers>[
  {
    "type": "damage", 
    "name": "THE END OF WILLPOWER, THE BEGINNING OF FEAR", 
    "description": "If Sinestro possesses this power after taking pushing damage, place a fear token on this card. Sinestro modifies his attack value by +1 for each fear token on this card. If Sinestro is healed, remove all fear tokens from this card."
  }
]</special_powers>
    <improved_movement>[]</improved_movement>
    <improved_targeting>[]</improved_targeting>
    <object_keyphrases>[]</object_keyphrases>
    <unit_range>9</unit_range>
    <targets>1</targets>
    <speed_type>wing</speed_type>
    <attack_type>fist</attack_type>
    <defense_type>shield</defense_type>
    <damage_type>starburst</damage_type>
    <dial_size>12</dial_size>
    <dial>[
  {
    "click_number": 1, 
    "starting_line": true, 
    "speed_power": "charge", 
    "speed_value": 11, 
    "attack_value": 10, 
    "defense_power": "willpower", 
    "defense_value": 19, 
    "damage_power": "exploit_weakness", 
    "damage_value": 3
  }, 
  {
    "click_number": 2, 
    "speed_power": "charge", 
    "speed_value": 10, 
    "attack_value": 10, 
    "defense_power": "willpower", 
    "defense_value": 18, 
    "damage_power": "exploit_weakness", 
    "damage_value": 3
  }, 
  {
    "click_number": 3, 
    "speed_power": "force_blast", 
    "speed_value": 10, 
    "attack_value": 9, 
    "defense_power": "energy_shield_deflection", 
    "defense_value": 17, 
    "damage_power": "special", 
    "damage_value": 3
  }, 
  {
    "click_number": 4, 
    "speed_power": "force_blast", 
    "speed_value": 9, 
    "attack_value": 9, 
    "defense_power": "energy_shield_deflection", 
    "defense_value": 16, 
    "damage_power": "special", 
    "damage_value": 3
  }, 
  {
    "click_number": 5, 
    "speed_power": "force_blast", 
    "speed_value": 9, 
    "attack_power": "penetrating_psychic_blast", 
    "attack_value": 9, 
    "defense_power": "energy_shield_deflection", 
    "defense_value": 16, 
    "damage_power": "special", 
    "damage_value": 3
  }, 
  {
    "click_number": 6, 
    "speed_power": "force_blast", 
    "speed_value": 8, 
    "attack_power": "penetrating_psychic_blast", 
    "attack_value": 8, 
    "defense_power": "invulnerability", 
    "defense_value": 16, 
    "damage_power": "special", 
    "damage_value": 2
  }, 
  {
    "click_number": 7, 
    "speed_power": "force_blast", 
    "speed_value": 8, 
    "attack_power": "penetrating_psychic_blast", 
    "attack_value": 8, 
    "defense_power": "invulnerability", 
    "defense_value": 16, 
    "damage_power": "special", 
    "damage_value": 2
  }, 
  {
    "click_number": 8, 
    "speed_power": "force_blast", 
    "speed_value": 8, 
    "attack_power": "penetrating_psychic_blast", 
    "attack_value": 8, 
    "defense_power": "invulnerability", 
    "defense_value": 16, 
    "damage_power": "special", 
    "damage_value": 2
  }
]</dial>
  </row>
  <row>
    <unit_id>ffgl005</unit_id>
    <set_id>ffgl</set_id>
    <collector_number>005</collector_number>
    <name>Guardian of the Universe</name>
    <type>character</type>
    <rarity>common</rarity>
    <dimensions>1x1</dimensions>
    <point_values>[150]</point_values>
    <properties>[]</properties>
    <team_abilities>[]</team_abilities>
    <keywords>["Cosmic", "Green Lantern Corps"]</keywords>
    <special_powers>[]</special_powers>
    <improved_movement>[]</improved_movement>
    <improved_targeting>[]</improved_targeting>
    <object_keyphrases>[]</object_keyphrases>
    <unit_range>10</unit_range>
    <targets>1</targets>
    <speed_type>wing</speed_type>
    <attack_type>fist</attack_type>
    <defense_type>indomitable</defense_type>
    <damage_type>starburst</damage_type>
    <dial_size>12</dial_size>
    <dial>[
  {
    "click_number": 1, 
    "starting_line": true, 
    "speed_power": "phasing_teleport", 
    "speed_value": 10, 
    "attack_power": "penetrating_psychic_blast", 
    "attack_value": 11, 
    "defense_power": "impervious", 
    "defense_value": 18, 
    "damage_power": "outwit", 
    "damage_value": 4
  }, 
  {
    "click_number": 2, 
    "speed_power": "phasing_teleport", 
    "speed_value": 10, 
    "attack_power": "penetrating_psychic_blast", 
    "attack_value": 10, 
    "defense_power": "impervious", 
    "defense_value": 18, 
    "damage_power": "outwit", 
    "damage_value": 4
  }, 
  {
    "click_number": 3, 
    "speed_value": 9, 
    "attack_power": "penetrating_psychic_blast", 
    "attack_value": 10, 
    "defense_power": "invulnerability", 
    "defense_value": 17, 
    "damage_value": 3
  }, 
  {
    "click_number": 4, 
    "speed_value": 8, 
    "attack_value": 10, 
    "defense_power": "invulnerability", 
    "defense_value": 17, 
    "damage_power": "probability_control", 
    "damage_value": 3
  }, 
  {
    "click_number": 5, 
    "speed_value": 8, 
    "attack_value": 9, 
    "defense_power": "toughness", 
    "defense_value": 17, 
    "damage_power": "probability_control", 
    "damage_value": 3
  }, 
  {
    "click_number": 6, 
    "speed_value": 9, 
    "attack_power": "pulse_wave", 
    "attack_value": 9, 
    "defense_power": "toughness", 
    "defense_value": 17, 
    "damage_value": 2
  }, 
  {
    "click_number": 7, 
    "speed_power": "phasing_teleport", 
    "speed_value": 10, 
    "attack_power": "pulse_wave", 
    "attack_value": 9, 
    "defense_power": "toughness", 
    "defense_value": 16, 
    "damage_power": "outwit", 
    "damage_value": 2
  }, 
  {
    "click_number": 8, 
    "speed_power": "phasing_teleport", 
    "speed_value": 10, 
    "attack_power": "pulse_wave", 
    "attack_value": 9, 
    "defense_power": "toughness", 
    "defense_value": 16, 
    "damage_power": "probability_control", 
    "damage_value": 2
  }
]</dial>
  </row>
  <row>
    <unit_id>ffgl006</unit_id>
    <set_id>ffgl</set_id>
    <collector_number>006</collector_number>
    <name>Abin Sur</name>
    <type>character</type>
    <rarity>common</rarity>
    <dimensions>1x1</dimensions>
    <point_values>[50]</point_values>
    <properties>[]</properties>
    <team_abilities>["green_lantern_corps"]</team_abilities>
    <keywords>["Green Lantern Corps", "Police"]</keywords>
    <special_powers>[
  {
    "type": "speed", 
    "name": "ALWAYS USES A SHIP", 
    "description": "If Abin Sur carries only one character, he can carry any single base character regardless of their combat symbols."
  }
]</special_powers>
    <improved_movement>[]</improved_movement>
    <improved_targeting>[]</improved_targeting>
    <object_keyphrases>[]</object_keyphrases>
    <unit_range>6</unit_range>
    <targets>1</targets>
    <speed_type>wing</speed_type>
    <attack_type>fist</attack_type>
    <defense_type>shield</defense_type>
    <damage_type>starburst</damage_type>
    <dial_size>12</dial_size>
    <dial>[
  {
    "click_number": 1, 
    "starting_line": true, 
    "speed_power": "special", 
    "speed_value": 11, 
    "attack_value": 9, 
    "defense_power": "super_senses", 
    "defense_value": 16, 
    "damage_value": 3
  }, 
  {
    "click_number": 2, 
    "speed_power": "special", 
    "speed_value": 10, 
    "attack_value": 9, 
    "defense_power": "super_senses", 
    "defense_value": 16, 
    "damage_value": 2
  }, 
  {
    "click_number": 3, 
    "speed_power": "special", 
    "speed_value": 10, 
    "attack_value": 9, 
    "defense_power": "super_senses", 
    "defense_value": 16, 
    "damage_value": 1
  }, 
  {
    "click_number": 4, 
    "speed_power": "earthbound_neutralized", 
    "speed_value": 9, 
    "attack_value": 9, 
    "defense_power": "barrier", 
    "defense_value": 15, 
    "damage_power": "ranged_combat_expert", 
    "damage_value": 1
  }, 
  {
    "click_number": 5, 
    "speed_power": "earthbound_neutralized", 
    "speed_value": 9, 
    "attack_value": 8, 
    "defense_power": "barrier", 
    "defense_value": 15, 
    "damage_power": "ranged_combat_expert", 
    "damage_value": 1
  }, 
  {
    "click_number": 6, 
    "speed_power": "earthbound_neutralized", 
    "speed_value": 9, 
    "attack_value": 8, 
    "defense_power": "barrier", 
    "defense_value": 15, 
    "damage_power": "ranged_combat_expert", 
    "damage_value": 1
  }
]</dial>
  </row>
  <row>
    <unit_id>ffglM001</unit_id>
    <set_id>ffgl</set_id>
    <collector_number>M001</collector_number>
    <name>Oa</name>
    <type>map</type>
    <point_values>[]</point_values>
    <properties>[]</properties>
    <team_abilities>[]</team_abilities>
    <keywords>[]</keywords>
    <special_powers>[]</special_powers>
    <improved_movement>[]</improved_movement>
    <improved_targeting>[]</improved_targeting>
    <object_keyphrases>[]</object_keyphrases>
    <map_url>https://hcmaps.net/maps/gl/oa.json</map_url>
    <dial>[]</dial>
  </row>
  <row>
    <unit_id>ffglM002</unit_id>
    <set_id>ffgl</set_id>
    <collector_number>M002</collector_number>
    <name>Ferris Aircraft</name>
    <type>map</type>
    <point_values>[]</point_values>
    <properties>[]</properties>
    <team_abilities>[]</team_abilities>
    <keywords>[]</keywords>
    <special_powers>[]</special_powers>
    <improved_movement>[]</improved_movement>
    <improved_targeting>[]</improved_targeting>
    <object_keyphrases>[]</object_keyphrases>
    <map_url>https://hcmaps.net/maps/gl/ferris_aircraft.json</map_url>
    <dial>[]</dial>
  </row>
</resultset>